{
  "date": "2026-07-02",
  "tasks": [
    {
      "id": "work",
      "name": "工作",
      "baseScore": 2,
      "increment": 1,
      "maxScore": 15,
      "isKeyTask": true,
      "sipScore": 2,
      "completed": false,
      "note": "下午镁业战略月会（如果开） / 或准备明天上半年工作总结"
    },
    {
      "id": "career",
      "name": "事业",
      "baseScore": 2,
      "increment": 1,
      "maxScore": 15,
      "isKeyTask": true,
      "sipScore": 2,
      "completed": true,
      "note": "发布镁期货文章到知乎（已写完，今天发，别再存着）；下午去工商银行办对公账户（已预约）；知乎回答 ≥2 个（保持节奏，单日涨粉已经验证）"
    },
    {
      "id": "self-improve",
      "name": "自我提升",
      "baseScore": 2,
      "increment": 1,
      "maxScore": 15,
      "isKeyTask": true,
      "sipScore": 2,
      "completed": false,
      "note": "继续读《人有人的用处》下一章"
    },
    {
      "id": "family",
      "name": "家庭生活",
      "baseScore": 2,
      "increment": 1,
      "maxScore": 10,
      "isKeyTask": false,
      "sipScore": 10,
      "completed": false,
      "note": ""
    },
    {
      "id": "initiative",
      "name": "主动性",
      "baseScore": 2,
      "increment": 1,
      "maxScore": 10,
      "isKeyTask": false,
      "sipScore": 7,
      "completed": false,
      "note": "找本地企业推销自己申报项目的能力（清单第8项——你已注册公司，有身份了）"
    },
    {
      "id": "exercise",
      "name": "锻炼节食",
      "baseScore": 2,
      "increment": 1,
      "maxScore": 10,
      "isKeyTask": false,
      "sipScore": 6,
      "completed": true,
      "note": ""
    },
    {
      "id": "early-rise",
      "name": "早起",
      "baseScore": 2,
      "increment": 1,
      "maxScore": 5,
      "isKeyTask": false,
      "sipScore": 5,
      "completed": true,
      "note": ""
    },
    {
      "id": "daily-note",
      "name": "日摘",
      "baseScore": 2,
      "increment": 1,
      "maxScore": 5,
      "isKeyTask": false,
      "sipScore": 4,
      "completed": false,
      "note": ""
    },
    {
      "id": "meditation",
      "name": "思考冥想",
      "baseScore": 2,
      "increment": 1,
      "maxScore": 5,
      "isKeyTask": false,
      "sipScore": 2,
      "completed": false,
      "note": ""
    }
  ],
  "totalScore": 298,
  "lastUpdated": "2026-07-02T01:55:17.001Z"
}